bibigo/__init__.py
bibigo/exceptions.py
bibigo/scripts.py
bibigo/utils.py
bibigo/init/__init__.py
bibigo/init/docker_compose.py
bibigo/init/package.py
bibigo/init/settings.py
bibigo/static/.dockerignore.default
bibigo/static/.gitignore.default
bibigo/static/Dockerfile.default
bibigo/static/MANIFEST.in.default
bibigo/static/__init__.py
bibigo/static/__init__.py.default
bibigo/static/docker-compose.yml.default
bibigo/static/example.py.default
bibigo/static/pyproject.toml.default
bibigo/static/scripts.py.default
bibigo/static/setup.cfg.default
bibigo/static/.vscode/__init__.py
bibigo/static/.vscode/settings.json.default
bibigo-2025.3.1.dist-info/LICENSE
bibigo-2025.3.1.dist-info/METADATA
bibigo-2025.3.1.dist-info/WHEEL
bibigo-2025.3.1.dist-info/entry_points.txt
bibigo-2025.3.1.dist-info/top_level.txt
bibigo-2025.3.1.dist-info/RECORD
