Metadata-Version: 2.2
Name: bibigo
Version: 2025.3.1
Summary: python templates
Author: Woojin Cho
Author-email: w.cho@cj.net
Requires-Python: >=3.8
License-File: LICENSE
Requires-Dist: rich
Requires-Dist: click
Requires-Dist: boto3
Requires-Dist: InquirerPy
